{"#mime-type":"infrastructure","#mime-types":"semantics","#mime-types-2":"index","#mime-types-2:application/microdata+json":"index","#mime-types-2:application/x-www-form-urlencoded":"index","#mime-types-2:application/xhtml+xml":"index","#mime-types-2:multipart/x-mixed-replace":"index","#mime-types-2:text/cache-manifest":"index","#mime-types-2:text/event-stream":"index","#mime-types-2:text/html":"index","#mime-types:a-type-that-the-user-agent-knows-it-cannot-render":"semantics","#mime-types:a-type-that-the-user-agent-knows-it-cannot-render-2":"semantics","#mime-types:application/octet-stream":"semantics","#mime-types:application/octet-stream-2":"semantics","#mime-types:application/octet-stream-3":"semantics","#mime-types:attr-source-type":"semantics","#mime-types:content-type":"semantics","#mime-types:dom-canplaytyperesult-maybe":"semantics","#mime-types:dom-canplaytyperesult-probably":"semantics","#mime-types:dom-navigator-canplaytype":"semantics","#mime-types:media-resource":"semantics","#mime-types:media-resource-2":"semantics","#mime-types:media-resource-3":"semantics","#mime-types:mime-type":"semantics","#mime-types:mime-type-2":"semantics","#mime-types:mime-type-3":"semantics","#mime-types:mime-type-4":"semantics","#mime-types:mime-type-5":"semantics","#mime-types:the-audio-element":"semantics","#mime-types:the-source-element":"semantics","#mime-types:the-video-element":"semantics","#mime-types:the-video-element-2":"semantics"}