{"#resolve-a-url":"infrastructure","#resolving-urls":"infrastructure","#resolving-urls:a-utf-16-encoding":"infrastructure","#resolving-urls:absolute-url":"infrastructure","#resolving-urls:absolute-url-2":"infrastructure","#resolving-urls:absolute-url-3":"infrastructure","#resolving-urls:absolute-url-4":"infrastructure","#resolving-urls:absolute-url-5":"infrastructure","#resolving-urls:api-url-character-encoding":"infrastructure","#resolving-urls:concept-url-serialiser":"infrastructure","#resolving-urls:document":"infrastructure","#resolving-urls:document's-character-encoding":"infrastructure","#resolving-urls:document-2":"infrastructure","#resolving-urls:document-3":"infrastructure","#resolving-urls:document-base-url":"infrastructure","#resolving-urls:html-documents":"infrastructure","#resolving-urls:relative-url":"infrastructure","#resolving-urls:settings-object":"infrastructure","#resolving-urls:the-element's-base-url":"infrastructure","#resolving-urls:the-xml:base-attribute-(xml-only)":"infrastructure","#resolving-urls:the-xml:base-attribute-(xml-only)-2":"infrastructure","#resolving-urls:url":"infrastructure","#resolving-urls:url-parser":"infrastructure","#resolving-urls:url-parser-2":"infrastructure"}